hedera_sdk_python-0.1.5.dist-info/METADATA
hedera_sdk_python-0.1.5.dist-info/WHEEL
hedera_sdk_python-0.1.5.dist-info/entry_points.txt
hedera_sdk_python-0.1.5.dist-info/licenses/LICENSE
hedera_sdk_python/__init__.py
hedera_sdk_python/account/__init__.py
hedera_sdk_python/account/account_balance.py
hedera_sdk_python/account/account_create_transaction.py
hedera_sdk_python/account/account_id.py
hedera_sdk_python/client/__init__.py
hedera_sdk_python/client/client.py
hedera_sdk_python/client/network.py
hedera_sdk_python/consensus/__init__.py
hedera_sdk_python/consensus/topic_create_transaction.py
hedera_sdk_python/consensus/topic_delete_transaction.py
hedera_sdk_python/consensus/topic_id.py
hedera_sdk_python/consensus/topic_info.py
hedera_sdk_python/consensus/topic_message.py
hedera_sdk_python/consensus/topic_message_submit_transaction.py
hedera_sdk_python/consensus/topic_update_transaction.py
hedera_sdk_python/crypto/__init__.py
hedera_sdk_python/crypto/private_key.py
hedera_sdk_python/crypto/public_key.py
hedera_sdk_python/hapi/mirror/__init__.py
hedera_sdk_python/hapi/services/__init__.py
hedera_sdk_python/hbar.py
hedera_sdk_python/query/__init__.py
hedera_sdk_python/query/account_balance_query.py
hedera_sdk_python/query/query.py
hedera_sdk_python/query/topic_info_query.py
hedera_sdk_python/query/topic_message_query.py
hedera_sdk_python/query/transaction_get_receipt_query.py
hedera_sdk_python/response_code.py
hedera_sdk_python/timestamp.py
hedera_sdk_python/tokens/__init__.py
hedera_sdk_python/tokens/token_associate_transaction.py
hedera_sdk_python/tokens/token_create_transaction.py
hedera_sdk_python/tokens/token_delete_transaction.py
hedera_sdk_python/tokens/token_dissociate_transaction.py
hedera_sdk_python/tokens/token_id.py
hedera_sdk_python/transaction/__init__.py
hedera_sdk_python/transaction/query_payment.py
hedera_sdk_python/transaction/transaction.py
hedera_sdk_python/transaction/transaction_id.py
hedera_sdk_python/transaction/transaction_receipt.py
hedera_sdk_python/transaction/transfer_transaction.py
hedera_sdk_python/utils/key_format.py
hedera_sdk_python-0.1.5.dist-info/RECORD
