Metadata-Version: 2.1
Name: hedera_sdk_python
Version: 0.1.5
Summary: A Hiero SDK in pure Python
Author-Email: Nadine Loepfe <nadine.loepfe@hashgraph.com>, Richard Bair <rbair23@users.noreply.github.com>
Maintainer-Email: Nadine Loepfe <nadine.loepfe@hashgraph.com>
License:                                  Apache License
Classifier: Development Status :: 2 - Pre-Alpha
Classifier: License :: OSI Approved :: Apache Software License
Classifier: Programming Language :: Python :: 3.9
Classifier: Operating System :: OS Independent
Classifier: Intended Audience :: Developers
Classifier: Topic :: Software Development :: Libraries :: Python Modules
Requires-Python: >=3.9.2
Requires-Dist: protobuf==5.28.1
Requires-Dist: grpcio-tools==1.68.1
Requires-Dist: grpcio==1.68.1
Requires-Dist: cryptography==44.0.0
Requires-Dist: python-dotenv==1.0.1
Requires-Dist: requests==2.32.3
